liku/__init__.py
liku/context.py
liku/elements.py
liku/html.py
liku/integrations/__init__.py
liku/integrations/flask.py
liku/py.typed
liku/signatures.py
liku-0.1.1.dist-info/LICENSE
liku-0.1.1.dist-info/METADATA
liku-0.1.1.dist-info/WHEEL
liku-0.1.1.dist-info/RECORD
